automatic_test_tool-0.2.3.data/purelib/automatic_test_tool/__init__.py
automatic_test_tool-0.2.3.data/purelib/automatic_test_tool/_base_page.cpython-37m-darwin.so
automatic_test_tool-0.2.3.data/purelib/automatic_test_tool/_custom_logger.cpython-37m-darwin.so
automatic_test_tool-0.2.3.data/purelib/automatic_test_tool/_util.cpython-37m-darwin.so
automatic_test_tool-0.2.3.data/purelib/automatic_test_tool/test_case.py
automatic_test_tool-0.2.3.dist-info/METADATA
automatic_test_tool-0.2.3.dist-info/WHEEL
automatic_test_tool-0.2.3.dist-info/top_level.txt
automatic_test_tool-0.2.3.dist-info/RECORD
