Metadata-Version: 2.1
Name: automatic-test-tool
Version: 0.2.3
Summary: Automatic web browser tests
Home-page: UNKNOWN
Author: aformeds
Author-email: geral@aformeds.pt
License: UNKNOWN
Keywords: pip,selenium,browser,automation,test
Platform: UNKNOWN
Requires-Dist: selenium (>=3.14.1)
Requires-Dist: pytest (>=4.0.0)
Requires-Dist: pytest-selenium (>=1.14.0)
